{
    "congruence": {
        "0": {},
        "328170849": {
            " 你是谁 ": [
                " 我是机器人立华奏"
            ],
            "主人": [
                "我主人是摸你傻",
                "我主人是摸你傻"
            ],
            "我是谁": [
                "魔理沙"
            ]
        },
        "695392621": {
            "你好": [
                "我是立华奏"
            ],
            "喜欢你": [
                "我也喜欢你"
            ],
            "主人": [
                "魔理沙"
            ],
            "[CQ:at,qq=1707906469] 我想草死你": [
                "让我舔你的肉棒吧"
            ]
        },
        "993105896": {
            "主人": [
                "我的主人是魔理沙"
            ]
        },
        "1062564756": {
            "主人": [
                "魔理沙"
            ],
            "[CQ:at,qq=1707906469] 我想草死你": [
                "让我舔你的肉棒吧"
            ],
            "[CQ:at,qq=1707906469] 动漫": [
                "呐呐~还看动漫呢，欸多~二次元真可爱捏"
            ],
            "动漫": [
                "呐呐~还看动漫呢，欸多~二次元真可爱捏"
            ]
        }
    },
    "include": {
        "0": {
            "[CQ:at,qq=1707906469] pip如何升级": [
                "python -m pip install --upgrade pip -i https://pypi.tuna.tsinghua.edu.cn/simple/\r\n或者pip install --user -- upgrade pip"
            ],
            "[CQ:at,qq=1707906469] PIL": [
                "pip3 install pillow\r\n安装"
            ]
        }
    },
    "regex": {
        "0": {}
    }
}